is3_analyse/__init__.py
is3_analyse/core/__init__.py
is3_analyse/core/api_exception.py
is3_analyse/core/base_result.py
is3_analyse/core/util.py
is3_analyse/server/__init__.py
is3_analyse/server/analyse_server.py
is3_analyse/server/base_algorithm.py
is3_analyse/server/exception_handle.py
is3_analyse/server/routes.py
is3_analyse-0.5.dist-info/LICENSE
is3_analyse-0.5.dist-info/METADATA
is3_analyse-0.5.dist-info/WHEEL
is3_analyse-0.5.dist-info/entry_points.txt
is3_analyse-0.5.dist-info/top_level.txt
is3_analyse-0.5.dist-info/RECORD
