Metadata-Version: 2.1
Name: is3_analyse
Version: 0.5
Summary: is3 python server
Home-page: https://github.com/ZhihengNing/Python-server
Author: Zhiheng Ning
Author-email: 
Classifier: Programming Language :: Python :: 3
Classifier: License :: OSI Approved :: MIT License
Classifier: Operating System :: OS Independent
License-File: LICENSE
Requires-Dist: Flask ==3.0.3
Requires-Dist: numpy ==1.26.4
